lgapp/__init__.py
lgapp/app.py
lgapp/core/__init__.py
lgapp/core/report.py
lgapp/core/test_runner.py
lgapp/pages/__init__.py
lgapp/pages/config_page.py
lgapp/pages/reports_page.py
lgapp/pages/run_page.py
lgapp/util/__init__.py
lgapp/util/local_file_picker.py
lgapp/util/paths.py
lgapp/util/pdf_service.py
lgapp/view/__init__.py
lgapp/view/dialogs.py
lgapp/view/header.py
lgapp/view/report_viewer.py
lgapp/view/reports_table.py
lgapp-1.0.0.dist-info/METADATA
lgapp-1.0.0.dist-info/WHEEL
lgapp-1.0.0.dist-info/entry_points.txt
lgapp-1.0.0.dist-info/licenses/LICENSE
lgapp-1.0.0.dist-info/RECORD
