Metadata-Version: 2.4
Name: lgapp
Version: 1.0.0
Summary: LGApp: GUI for Labgrid
Author-email: Mahyar Shariat <shariatmahyar@gmail.com>
License: MIT
License-File: LICENSE
Requires-Python: >=3.10
Requires-Dist: junit-xml
Requires-Dist: junit2html
Requires-Dist: labgrid
Requires-Dist: nicegui
Requires-Dist: platformdirs
Requires-Dist: pytest
Requires-Dist: pytest-html
Requires-Dist: tortoise-orm
Requires-Dist: weasyprint
